embuild_colorize/__init__.py
embuild_colorize/__main__.py
embuild_colorize/colorize.py
embuild_colorize/version.py
embuild_colorize-0.1.4.dist-info/METADATA
embuild_colorize-0.1.4.dist-info/WHEEL
embuild_colorize-0.1.4.dist-info/entry_points.txt
embuild_colorize-0.1.4.dist-info/top_level.txt
embuild_colorize-0.1.4.dist-info/RECORD
